{
  "version": 0.1,
  "generated_utc": "2026-03-19T11:12:03.583444Z",
  "item_id": "l2_prop_l2_mapper_terminal_vecop_direct_output_v1_nm1_fused_r1",
  "run_key": "l2_prop_l2_mapper_terminal_vecop_direct_output_v1_nm1_fused_r1_run_9ca3905be8de3980",
  "layer": "layer2",
  "flow": "openroad",
  "platform": "nangate45",
  "task_type": "l2_campaign",
  "source_commit": "af4d14017f2568428121ea9c9516c6284ffcc66b",
  "objective": "terminal_vecop_direct_output_vs_nonfused",
  "input_manifest": {
    "sweeps": [
      "runs/designs/npu_blocks/npu_fp16_cpp_nm1_cmp/sweep_compare_33.json"
    ],
    "configs": [
      "runs/designs/npu_blocks/npu_fp16_cpp_nm1_cmp/config_nm1.json"
    ],
    "design_dirs": [
      "runs/designs/npu_blocks/npu_fp16_cpp_nm1_cmp"
    ],
    "macro_manifests": [
      "runs/designs/npu_macros/gemm_compute_array_fp16_nm1_c250/macro_manifest.json"
    ],
    "generated_campaign": {
      "path": "runs/campaigns/npu/e2e_eval_onnx_terminal_vecop_suite_fused_nm1_v1/campaign__l2_prop_l2_mapper_terminal_vecop_direct_output_v1_nm1_fused_r1.json",
      "outputs": {
        "report_md": "runs/campaigns/npu/e2e_eval_onnx_terminal_vecop_suite_fused_nm1_v1__l2_prop_l2_mapper_terminal_vecop_direct_output_v1_nm1_fused_r1/report.md",
        "results_csv": "runs/campaigns/npu/e2e_eval_onnx_terminal_vecop_suite_fused_nm1_v1__l2_prop_l2_mapper_terminal_vecop_direct_output_v1_nm1_fused_r1/results.csv",
        "campaign_dir": "runs/campaigns/npu/e2e_eval_onnx_terminal_vecop_suite_fused_nm1_v1__l2_prop_l2_mapper_terminal_vecop_direct_output_v1_nm1_fused_r1"
      },
      "base_campaign_path": "runs/campaigns/npu/e2e_eval_onnx_terminal_vecop_suite_fused_nm1_v1/campaign.json"
    },
    "candidate_manifests": [
      "runs/candidates/nangate45/module_candidates.json"
    ]
  },
  "recommendation": {
    "arch_id": "fp16_nm1",
    "macro_mode": "flat_nomacro",
    "objective_rank": 1,
    "objective_score": "0.0",
    "latency_ms_mean": 0.0052699999999999995,
    "energy_mj_mean": 1.01775294e-06,
    "critical_path_ns_mean": 5.557037432204143,
    "die_area_um2_mean": 2250000.0,
    "total_power_mw_mean": 0.193122,
    "flow_elapsed_s_mean": 844.5733333333334
  },
  "objective_profiles": [],
  "evaluation_record": {
    "proposal_id": "prop_l2_mapper_terminal_vecop_direct_output_v1",
    "title": "Terminal vec-op direct output",
    "primary_question": "Can a bounded terminal vec-op family establish clean nm1 reference points first, then show a direct-output win on those same points without reopening broader ranking?",
    "evaluation_mode": "paired_comparison",
    "comparison_role": "candidate",
    "expected_direction": "better_than_historical",
    "expected_reason": "Direct terminal vec-op output should reduce the final writeback tail on at least part of the bounded standalone terminal ReLU suite.",
    "summary": "Focused comparison improved latency and/or energy without regressing matched rows.",
    "baseline_ref": "runs/campaigns/npu/e2e_eval_onnx_terminal_vecop_suite_submit_nm1_v1__l2_prop_l2_mapper_terminal_vecop_direct_output_v1_nm1_measurement_r2",
    "baseline_item_id": "l2_prop_l2_mapper_terminal_vecop_direct_output_v1_nm1_measurement_r2",
    "outcome": "improved",
    "expectation_status": "as_expected"
  },
  "proposal_assessment": {
    "proposal_id": "prop_l2_mapper_terminal_vecop_direct_output_v1",
    "title": "Terminal vec-op direct output",
    "kind": "mapper",
    "primary_question": "Can a bounded terminal vec-op family establish clean nm1 reference points first, then show a direct-output win on those same points without reopening broader ranking?",
    "evaluation_mode": "paired_comparison",
    "comparison_role": "candidate",
    "outcome": "improved",
    "summary": "Focused comparison improved latency and/or energy without regressing matched rows.",
    "baseline_ref": "runs/campaigns/npu/e2e_eval_onnx_terminal_vecop_suite_submit_nm1_v1__l2_prop_l2_mapper_terminal_vecop_direct_output_v1_nm1_measurement_r2",
    "baseline_item_id": "l2_prop_l2_mapper_terminal_vecop_direct_output_v1_nm1_measurement_r2",
    "matched_row_count": 8,
    "matched_rows": [
      {
        "scope": "model",
        "arch_id": "fp16_nm1",
        "macro_mode": "flat_nomacro",
        "model_id": "relu_vec_b128_f64",
        "metrics": {
          "latency_ms_mean": {
            "baseline": 0.0022979999999999997,
            "candidate": 0.001686,
            "delta": -0.0006119999999999997
          },
          "energy_mj_mean": {
            "baseline": 4.43794356e-07,
            "candidate": 3.25603692e-07,
            "delta": -1.18190664e-07
          },
          "critical_path_ns_mean": {
            "baseline": 5.557037432204143,
            "candidate": 5.557037432204143,
            "delta": 0.0
          },
          "total_power_mw_mean": {
            "baseline": 0.193122,
            "candidate": 0.193122,
            "delta": 0.0
          },
          "flow_elapsed_s_mean": {
            "baseline": 844.5733333333334,
            "candidate": 844.5733333333334,
            "delta": 0.0
          },
          "throughput_infer_per_s_mean": {
            "baseline": 435161.0095735423,
            "candidate": 593119.8102016607,
            "delta": 157958.80062811845
          }
        }
      },
      {
        "scope": "model",
        "arch_id": "fp16_nm1",
        "macro_mode": "flat_nomacro",
        "model_id": "relu_vec_b256_f256",
        "metrics": {
          "latency_ms_mean": {
            "baseline": 0.016634,
            "candidate": 0.012438,
            "delta": -0.004196
          },
          "energy_mj_mean": {
            "baseline": 3.212391348e-06,
            "candidate": 2.402051436e-06,
            "delta": -8.10339912e-07
          },
          "critical_path_ns_mean": {
            "baseline": 5.557037432204143,
            "candidate": 5.557037432204143,
            "delta": 0.0
          },
          "total_power_mw_mean": {
            "baseline": 0.193122,
            "candidate": 0.193122,
            "delta": 0.0
          },
          "flow_elapsed_s_mean": {
            "baseline": 844.5733333333334,
            "candidate": 844.5733333333334,
            "delta": 0.0
          },
          "throughput_infer_per_s_mean": {
            "baseline": 60117.83094865937,
            "candidate": 80398.77793857534,
            "delta": 20280.946989915967
          }
        }
      },
      {
        "scope": "model",
        "arch_id": "fp16_nm1",
        "macro_mode": "flat_nomacro",
        "model_id": "relu_vec_flatten_b128_2x4x8",
        "metrics": {
          "latency_ms_mean": {
            "baseline": 0.0022979999999999997,
            "candidate": 0.001686,
            "delta": -0.0006119999999999997
          },
          "energy_mj_mean": {
            "baseline": 4.43794356e-07,
            "candidate": 3.25603692e-07,
            "delta": -1.18190664e-07
          },
          "critical_path_ns_mean": {
            "baseline": 5.557037432204143,
            "candidate": 5.557037432204143,
            "delta": 0.0
          },
          "total_power_mw_mean": {
            "baseline": 0.193122,
            "candidate": 0.193122,
            "delta": 0.0
          },
          "flow_elapsed_s_mean": {
            "baseline": 844.5733333333334,
            "candidate": 844.5733333333334,
            "delta": 0.0
          },
          "throughput_infer_per_s_mean": {
            "baseline": 435161.0095735423,
            "candidate": 593119.8102016607,
            "delta": 157958.80062811845
          }
        }
      },
      {
        "scope": "model",
        "arch_id": "fp16_nm1",
        "macro_mode": "hier_macro",
        "model_id": "relu_vec_b128_f64",
        "metrics": {
          "latency_ms_mean": {
            "baseline": 0.0022979999999999997,
            "candidate": 0.001686,
            "delta": -0.0006119999999999997
          },
          "energy_mj_mean": {
            "baseline": 4.537194180000001e-07,
            "candidate": 3.3288552600000003e-07,
            "delta": -1.2083389200000004e-07
          },
          "critical_path_ns_mean": {
            "baseline": 5.774905724664045,
            "candidate": 5.774905724664045,
            "delta": 0.0
          },
          "total_power_mw_mean": {
            "baseline": 0.197441,
            "candidate": 0.197441,
            "delta": 0.0
          },
          "flow_elapsed_s_mean": {
            "baseline": 976.8733333333333,
            "candidate": 976.8733333333333,
            "delta": 0.0
          },
          "throughput_infer_per_s_mean": {
            "baseline": 435161.0095735423,
            "candidate": 593119.8102016607,
            "delta": 157958.80062811845
          }
        }
      },
      {
        "scope": "model",
        "arch_id": "fp16_nm1",
        "macro_mode": "hier_macro",
        "model_id": "relu_vec_b256_f256",
        "metrics": {
          "latency_ms_mean": {
            "baseline": 0.016634,
            "candidate": 0.012438,
            "delta": -0.004196
          },
          "energy_mj_mean": {
            "baseline": 3.2842335940000008e-06,
            "candidate": 2.455771158e-06,
            "delta": -8.284624360000007e-07
          },
          "critical_path_ns_mean": {
            "baseline": 5.774905724664045,
            "candidate": 5.774905724664045,
            "delta": 0.0
          },
          "total_power_mw_mean": {
            "baseline": 0.197441,
            "candidate": 0.197441,
            "delta": 0.0
          },
          "flow_elapsed_s_mean": {
            "baseline": 976.8733333333333,
            "candidate": 976.8733333333333,
            "delta": 0.0
          },
          "throughput_infer_per_s_mean": {
            "baseline": 60117.83094865937,
            "candidate": 80398.77793857534,
            "delta": 20280.946989915967
          }
        }
      },
      {
        "scope": "model",
        "arch_id": "fp16_nm1",
        "macro_mode": "hier_macro",
        "model_id": "relu_vec_flatten_b128_2x4x8",
        "metrics": {
          "latency_ms_mean": {
            "baseline": 0.0022979999999999997,
            "candidate": 0.001686,
            "delta": -0.0006119999999999997
          },
          "energy_mj_mean": {
            "baseline": 4.537194180000001e-07,
            "candidate": 3.3288552600000003e-07,
            "delta": -1.2083389200000004e-07
          },
          "critical_path_ns_mean": {
            "baseline": 5.774905724664045,
            "candidate": 5.774905724664045,
            "delta": 0.0
          },
          "total_power_mw_mean": {
            "baseline": 0.197441,
            "candidate": 0.197441,
            "delta": 0.0
          },
          "flow_elapsed_s_mean": {
            "baseline": 976.8733333333333,
            "candidate": 976.8733333333333,
            "delta": 0.0
          },
          "throughput_infer_per_s_mean": {
            "baseline": 435161.0095735423,
            "candidate": 593119.8102016607,
            "delta": 157958.80062811845
          }
        }
      },
      {
        "scope": "aggregate",
        "arch_id": "fp16_nm1",
        "macro_mode": "flat_nomacro",
        "model_id": null,
        "metrics": {
          "latency_ms_mean": {
            "baseline": 0.007076666666666666,
            "candidate": 0.0052699999999999995,
            "delta": -0.0018066666666666665
          },
          "energy_mj_mean": {
            "baseline": 1.36666002e-06,
            "candidate": 1.01775294e-06,
            "delta": -3.4890708e-07
          },
          "critical_path_ns_mean": {
            "baseline": 5.557037432204143,
            "candidate": 5.557037432204143,
            "delta": 0.0
          },
          "total_power_mw_mean": {
            "baseline": 0.193122,
            "candidate": 0.193122,
            "delta": 0.0
          },
          "flow_elapsed_s_mean": {
            "baseline": 844.5733333333334,
            "candidate": 844.5733333333334,
            "delta": 0.0
          },
          "throughput_infer_per_s_mean": {
            "baseline": 310146.6166985813,
            "candidate": 422212.799447299,
            "delta": 112066.18274871766
          }
        }
      },
      {
        "scope": "aggregate",
        "arch_id": "fp16_nm1",
        "macro_mode": "hier_macro",
        "model_id": null,
        "metrics": {
          "latency_ms_mean": {
            "baseline": 0.007076666666666666,
            "candidate": 0.0052699999999999995,
            "delta": -0.0018066666666666665
          },
          "energy_mj_mean": {
            "baseline": 1.3972241433333337e-06,
            "candidate": 1.04051407e-06,
            "delta": -3.5671007333333364e-07
          },
          "critical_path_ns_mean": {
            "baseline": 5.774905724664045,
            "candidate": 5.774905724664045,
            "delta": 0.0
          },
          "total_power_mw_mean": {
            "baseline": 0.197441,
            "candidate": 0.197441,
            "delta": 0.0
          },
          "flow_elapsed_s_mean": {
            "baseline": 976.8733333333333,
            "candidate": 976.8733333333333,
            "delta": 0.0
          },
          "throughput_infer_per_s_mean": {
            "baseline": 310146.6166985813,
            "candidate": 422212.799447299,
            "delta": 112066.18274871766
          }
        }
      }
    ]
  },
  "source_refs": {
    "best_point_json": "runs/campaigns/npu/e2e_eval_onnx_terminal_vecop_suite_fused_nm1_v1__l2_prop_l2_mapper_terminal_vecop_direct_output_v1_nm1_fused_r1/best_point.json",
    "summary_csv": "runs/campaigns/npu/e2e_eval_onnx_terminal_vecop_suite_fused_nm1_v1__l2_prop_l2_mapper_terminal_vecop_direct_output_v1_nm1_fused_r1/summary.csv",
    "results_csv": "runs/campaigns/npu/e2e_eval_onnx_terminal_vecop_suite_fused_nm1_v1__l2_prop_l2_mapper_terminal_vecop_direct_output_v1_nm1_fused_r1/results.csv",
    "report_md": "runs/campaigns/npu/e2e_eval_onnx_terminal_vecop_suite_fused_nm1_v1__l2_prop_l2_mapper_terminal_vecop_direct_output_v1_nm1_fused_r1/report.md",
    "focused_candidate_schedule_yml": "runs/campaigns/npu/e2e_eval_onnx_terminal_vecop_suite_fused_nm1_v1__l2_prop_l2_mapper_terminal_vecop_direct_output_v1_nm1_fused_r1/artifacts/mapper/fp16_nm1/relu_vec_b128_f64/schedule.yml",
    "focused_candidate_descriptors_bin": "runs/campaigns/npu/e2e_eval_onnx_terminal_vecop_suite_fused_nm1_v1__l2_prop_l2_mapper_terminal_vecop_direct_output_v1_nm1_fused_r1/artifacts/mapper/fp16_nm1/relu_vec_b128_f64/descriptors.bin",
    "focused_candidate_perf_trace_json": "runs/campaigns/npu/e2e_eval_onnx_terminal_vecop_suite_fused_nm1_v1__l2_prop_l2_mapper_terminal_vecop_direct_output_v1_nm1_fused_r1/artifacts/perf/fp16_nm1/relu_vec_b128_f64/trace.json",
    "focused_model_artifacts": [
      {
        "model_id": "relu_vec_b128_f64",
        "schedule_yml": "runs/campaigns/npu/e2e_eval_onnx_terminal_vecop_suite_fused_nm1_v1__l2_prop_l2_mapper_terminal_vecop_direct_output_v1_nm1_fused_r1/artifacts/mapper/fp16_nm1/relu_vec_b128_f64/schedule.yml",
        "descriptors_bin": "runs/campaigns/npu/e2e_eval_onnx_terminal_vecop_suite_fused_nm1_v1__l2_prop_l2_mapper_terminal_vecop_direct_output_v1_nm1_fused_r1/artifacts/mapper/fp16_nm1/relu_vec_b128_f64/descriptors.bin",
        "perf_trace_json": "runs/campaigns/npu/e2e_eval_onnx_terminal_vecop_suite_fused_nm1_v1__l2_prop_l2_mapper_terminal_vecop_direct_output_v1_nm1_fused_r1/artifacts/perf/fp16_nm1/relu_vec_b128_f64/trace.json"
      },
      {
        "model_id": "relu_vec_b256_f256",
        "schedule_yml": "runs/campaigns/npu/e2e_eval_onnx_terminal_vecop_suite_fused_nm1_v1__l2_prop_l2_mapper_terminal_vecop_direct_output_v1_nm1_fused_r1/artifacts/mapper/fp16_nm1/relu_vec_b256_f256/schedule.yml",
        "descriptors_bin": "runs/campaigns/npu/e2e_eval_onnx_terminal_vecop_suite_fused_nm1_v1__l2_prop_l2_mapper_terminal_vecop_direct_output_v1_nm1_fused_r1/artifacts/mapper/fp16_nm1/relu_vec_b256_f256/descriptors.bin",
        "perf_trace_json": "runs/campaigns/npu/e2e_eval_onnx_terminal_vecop_suite_fused_nm1_v1__l2_prop_l2_mapper_terminal_vecop_direct_output_v1_nm1_fused_r1/artifacts/perf/fp16_nm1/relu_vec_b256_f256/trace.json"
      },
      {
        "model_id": "relu_vec_flatten_b128_2x4x8",
        "schedule_yml": "runs/campaigns/npu/e2e_eval_onnx_terminal_vecop_suite_fused_nm1_v1__l2_prop_l2_mapper_terminal_vecop_direct_output_v1_nm1_fused_r1/artifacts/mapper/fp16_nm1/relu_vec_flatten_b128_2x4x8/schedule.yml",
        "descriptors_bin": "runs/campaigns/npu/e2e_eval_onnx_terminal_vecop_suite_fused_nm1_v1__l2_prop_l2_mapper_terminal_vecop_direct_output_v1_nm1_fused_r1/artifacts/mapper/fp16_nm1/relu_vec_flatten_b128_2x4x8/descriptors.bin",
        "perf_trace_json": "runs/campaigns/npu/e2e_eval_onnx_terminal_vecop_suite_fused_nm1_v1__l2_prop_l2_mapper_terminal_vecop_direct_output_v1_nm1_fused_r1/artifacts/perf/fp16_nm1/relu_vec_flatten_b128_2x4x8/trace.json"
      }
    ],
    "baseline_summary_csv": "runs/campaigns/npu/e2e_eval_onnx_terminal_vecop_suite_submit_nm1_v1__l2_prop_l2_mapper_terminal_vecop_direct_output_v1_nm1_measurement_r2/summary.csv",
    "baseline_report_md": "runs/campaigns/npu/e2e_eval_onnx_terminal_vecop_suite_submit_nm1_v1__l2_prop_l2_mapper_terminal_vecop_direct_output_v1_nm1_measurement_r2/report.md"
  }
}
